xformers/_C.pyd
xformers/__init__.py
xformers/_cpp_lib.py
xformers/_deprecation_warning.py
xformers/attn_bias_utils.py
xformers/checkpoint.py
xformers/cpp_lib.json
xformers/fwbw_overlap.py
xformers/info.py
xformers/test.py
xformers/utils.py
xformers/version.py
xformers/benchmarks/__init__.py
xformers/benchmarks/benchmark_attn_decoding.py
xformers/benchmarks/benchmark_indexing.py
xformers/benchmarks/benchmark_mem_eff_attention.py
xformers/benchmarks/benchmark_merge_attentions.py
xformers/benchmarks/benchmark_sequence_parallel_fused.py
xformers/benchmarks/benchmark_sp24.py
xformers/benchmarks/benchmark_tiled_matmul.py
xformers/benchmarks/utils.py
xformers/flash_attn_3/_C.pyd
xformers/flash_attn_3/__init__.py
xformers/ops/__init__.py
xformers/ops/common.py
xformers/ops/differentiable_collectives.py
xformers/ops/indexing.py
xformers/ops/modpar_layers.py
xformers/ops/rmsnorm.py
xformers/ops/rope_padded.py
xformers/ops/seqpar.py
xformers/ops/sequence_parallel_fused_ops.py
xformers/ops/sp24.py
xformers/ops/swiglu_op.py
xformers/ops/tiled_matmul.py
xformers/ops/tree_attention.py
xformers/ops/unbind.py
xformers/ops/_triton/__init__.py
xformers/ops/_triton/k_index_select_cat.py
xformers/ops/_triton/k_scaled_index_add.py
xformers/ops/_triton/matmul_perf_model.py
xformers/ops/_triton/rmsnorm_kernels.py
xformers/ops/_triton/rope_padded_kernels.py
xformers/ops/_triton/tiled_matmul_kernels.py
xformers/ops/fmha/__init__.py
xformers/ops/fmha/attn_bias.py
xformers/ops/fmha/ck.py
xformers/ops/fmha/ck_splitk.py
xformers/ops/fmha/common.py
xformers/ops/fmha/cutlass.py
xformers/ops/fmha/cutlass_blackwell.py
xformers/ops/fmha/dispatch.py
xformers/ops/fmha/flash.py
xformers/ops/fmha/flash3.py
xformers/ops/fmha/merge_training.py
xformers/ops/fmha/torch_attention_compat.py
xformers/ops/fmha/triton_splitk.py
xformers/ops/fmha/_triton/__init__.py
xformers/ops/fmha/_triton/splitk_kernels.py
xformers/profiler/__init__.py
xformers/profiler/api.py
xformers/profiler/device_limits.py
xformers-0.0.34.dist-info/LICENSE
xformers-0.0.34.dist-info/METADATA
xformers-0.0.34.dist-info/WHEEL
xformers-0.0.34.dist-info/top_level.txt
xformers-0.0.34.dist-info/RECORD
