Metadata-Version: 2.1
Name: xformers
Version: 0.0.34
Summary: XFormers: A collection of composable Transformer building blocks.
Home-page: https://facebookresearch.github.io/xformers/
Author: Facebook AI Research
Author-email: oncall+xformers@xmail.facebook.com
Classifier: Programming Language :: Python :: 3.9
Classifier: Programming Language :: Python :: 3.10
Classifier: Programming Language :: Python :: 3.11
Classifier: Programming Language :: Python :: 3.12
Classifier: License :: OSI Approved :: BSD License
Classifier: Topic :: Scientific/Engineering :: Artificial Intelligence
Classifier: Operating System :: OS Independent
Requires-Python: >=3.9
License-File: LICENSE
Requires-Dist: numpy
Requires-Dist: torch==2.10.0
